you_track_rest_api_client/__init__.py
you_track_rest_api_client/api/__init__.py
you_track_rest_api_client/api/default/__init__.py
you_track_rest_api_client/api/default/delete_admin_custom_field_settings_bundles_build_id.py
you_track_rest_api_client/api/default/delete_admin_custom_field_settings_bundles_build_id_values_build_bundle_element_id.py
you_track_rest_api_client/api/default/delete_admin_custom_field_settings_bundles_enum_id.py
you_track_rest_api_client/api/default/delete_admin_custom_field_settings_bundles_enum_id_values_enum_bundle_element_id.py
you_track_rest_api_client/api/default/delete_admin_custom_field_settings_bundles_owned_field_id.py
you_track_rest_api_client/api/default/delete_admin_custom_field_settings_bundles_owned_field_id_values_owned_bundle_element_id.py
you_track_rest_api_client/api/default/delete_admin_custom_field_settings_bundles_state_id.py
you_track_rest_api_client/api/default/delete_admin_custom_field_settings_bundles_state_id_values_state_bundle_element_id.py
you_track_rest_api_client/api/default/delete_admin_custom_field_settings_bundles_user_id.py
you_track_rest_api_client/api/default/delete_admin_custom_field_settings_bundles_user_id_groups_user_group_id.py
you_track_rest_api_client/api/default/delete_admin_custom_field_settings_bundles_user_id_individuals_user_id.py
you_track_rest_api_client/api/default/delete_admin_custom_field_settings_bundles_version_id.py
you_track_rest_api_client/api/default/delete_admin_custom_field_settings_bundles_version_id_values_version_bundle_element_id.py
you_track_rest_api_client/api/default/delete_admin_custom_field_settings_custom_fields_id.py
you_track_rest_api_client/api/default/delete_admin_projects_id.py
you_track_rest_api_client/api/default/delete_admin_projects_id_custom_fields_project_custom_field_id.py
you_track_rest_api_client/api/default/delete_admin_projects_id_issues_issue_id.py
youtrack_python_openapi-2023.1.dist-info/WHEEL
youtrack_python_openapi-2023.1.dist-info/METADATA
youtrack_python_openapi-2023.1.dist-info/RECORD
